setup.py
platonic_solids_Carlos/__init__.py
platonic_solids_Carlos/measures.py
platonic_solids_Carlos/parts.py
platonic_solids_Carlos/radius.py
platonic_solids_Carlos.egg-info/PKG-INFO
platonic_solids_Carlos.egg-info/SOURCES.txt
platonic_solids_Carlos.egg-info/dependency_links.txt
platonic_solids_Carlos.egg-info/not-zip-safe
platonic_solids_Carlos.egg-info/top_level.txt