Metadata-Version: 2.1
Name: platonic-solids-Carlos
Version: 0.1
Summary: Solidos platonicos de Gonzalo
Author-email: carlosalonsobonilla@gmail.com
License: UNKNOWN
Platform: UNKNOWN
